ccs_digitalmarketplace_frontend_jinja-4.17.1.dist-info/licenses/LICENCE
digitalmarketplace_frontend_jinja/__init__.py
digitalmarketplace_frontend_jinja/templates/components/alert/macro.html
digitalmarketplace_frontend_jinja/templates/components/attachment/macro.html
digitalmarketplace_frontend_jinja/templates/components/banner/macro.html
digitalmarketplace_frontend_jinja/templates/components/character-count-from-form/macro.html
digitalmarketplace_frontend_jinja/templates/components/checkboxes-from-form/macro.html
digitalmarketplace_frontend_jinja/templates/components/compliance-communication-attachment-row/macro.html
digitalmarketplace_frontend_jinja/templates/components/compliance-communication-attachments/macro.html
digitalmarketplace_frontend_jinja/templates/components/cookie-banner/macro.html
digitalmarketplace_frontend_jinja/templates/components/date-input-from-form/macro.html
digitalmarketplace_frontend_jinja/templates/components/documents/macro.html
digitalmarketplace_frontend_jinja/templates/components/file-upload-from-form/macro.html
digitalmarketplace_frontend_jinja/templates/components/footer/macro.html
digitalmarketplace_frontend_jinja/templates/components/header/macro.html
digitalmarketplace_frontend_jinja/templates/components/input-from-form/macro.html
digitalmarketplace_frontend_jinja/templates/components/list-input/macro.html
digitalmarketplace_frontend_jinja/templates/components/option-select/macro.html
digitalmarketplace_frontend_jinja/templates/components/previous-next-pagination/macro.html
digitalmarketplace_frontend_jinja/templates/components/question/macro.html
digitalmarketplace_frontend_jinja/templates/components/question-boolean/macro.html
digitalmarketplace_frontend_jinja/templates/components/question-character-count/macro.html
digitalmarketplace_frontend_jinja/templates/components/question-checkbox-tree/macro.html
digitalmarketplace_frontend_jinja/templates/components/question-checkbox-tree-large/macro.html
digitalmarketplace_frontend_jinja/templates/components/question-checkboxes/macro.html
ccs_digitalmarketplace_frontend_jinja-4.17.1.dist-info/METADATA
ccs_digitalmarketplace_frontend_jinja-4.17.1.dist-info/WHEEL
ccs_digitalmarketplace_frontend_jinja-4.17.1.dist-info/top_level.txt
ccs_digitalmarketplace_frontend_jinja-4.17.1.dist-info/RECORD
