Metadata-Version: 2.4
Name: ccs-digitalmarketplace-frontend-jinja
Version: 4.17.1
Summary: Jinja templates for Digital Marketplace apps.
Author: CCS Developers
Project-URL: Homepage, https://github.com/Crown-Commercial-Service/ccs-digitalmarketplace-frontend-jinja
Project-URL: Repository, https://github.com/Crown-Commercial-Service/ccs-digitalmarketplace-frontend-jinja.git
Project-URL: Issues, https://github.com/Crown-Commercial-Service/ccs-digitalmarketplace-frontend-jinja/issues
Project-URL: Changelog, https://github.com/Crown-Commercial-Service/ccs-digitalmarketplace-frontend-jinja/CHANGELOG.md
Requires-Python: <3.15,>=3.11
License-File: LICENCE
Requires-Dist: jinja2>3
Requires-Dist: govuk-frontend-jinja<4,>=3.10
Requires-Dist: ccs-digitalmarketplace-utils>=79.8.0
Provides-Extra: dev
Requires-Dist: ruff==0.14.13; extra == "dev"
Requires-Dist: mypy==1.19.1; extra == "dev"
Requires-Dist: pytest==9.0.2; extra == "dev"
Requires-Dist: lxml==6.0.2; extra == "dev"
Requires-Dist: xmldiff==2.7.0; extra == "dev"
Requires-Dist: flask==3.1.2; extra == "dev"
Requires-Dist: pre-commit==4.5.1; extra == "dev"
Dynamic: license-file
